keyauth_renee/__init__.py
keyauth_renee/core.py
keyauth_renee-0.2.0.dist-info/licenses/LICENSE
keyauth_renee-0.2.0.dist-info/METADATA
keyauth_renee-0.2.0.dist-info/WHEEL
keyauth_renee-0.2.0.dist-info/top_level.txt
keyauth_renee-0.2.0.dist-info/RECORD
